fetchproref
