Metadata-Version: 1.1
Name: fetchproref
Version: 0.0.4
Summary: A command-line tool that downloads all table from a Pro Reference site
Home-page: https://github.com/lazarogamio/fetchproref
Author: Lazaro Gamio
Author-email: lazaro.gamio@gmail.com
License: MIT
Platform: UNKNOWN
Classifier: Development Status :: 4 - Beta
Classifier: Environment :: Console
Classifier: Intended Audience :: Developers
Classifier: License :: OSI Approved :: MIT License
Classifier: Natural Language :: English
Classifier: Operating System :: Unix
Classifier: Programming Language :: Python
Classifier: Topic :: Software Development
